PyTools/__init__.py
PyTools/http.py
python_tools-0.0.1.dist-info/LICENSE
python_tools-0.0.1.dist-info/METADATA
python_tools-0.0.1.dist-info/WHEEL
python_tools-0.0.1.dist-info/top_level.txt
python_tools-0.0.1.dist-info/RECORD
