Metadata-Version: 2.1
Name: python-tools
Version: 0.0.1
Summary: 开发爬虫常用的工具类
Home-page: https://github.com/dapengcode/PyTools
Author: DaPeng
Author-email: davidmaster@163.com
License: UNKNOWN
Platform: UNKNOWN
Classifier: Programming Language :: Python :: 3
Classifier: License :: OSI Approved :: MIT License
Classifier: Operating System :: OS Independent
Requires-Python: >=3.6
